acl/__init__.py
acl/__main__.py
acl/py.typed
acl/annotation_zip/__init__.py
acl/command/__init__.py
acl/command/validate_attribute_value.py
acl/common/__init__.py
acl/common/cli.py
acl/common/constants.py
acl/common/utils.py
acl/common/xdg_util.py
acl/common/annofab/__init__.py
acl/common/annofab/annotation_specs.py
acl/common/annofab/project.py
annofabcli_llm-0.1.2.dist-info/METADATA
annofabcli_llm-0.1.2.dist-info/WHEEL
annofabcli_llm-0.1.2.dist-info/entry_points.txt
annofabcli_llm-0.1.2.dist-info/licenses/LICENSE
annofabcli_llm-0.1.2.dist-info/RECORD
