Metadata-Version: 2.4
Name: annofabcli-llm
Version: 0.1.2
Summary: LLMとannofab-cliを組み合わせたツールです。
Author: Kurusugawa Computer Inc.
License: MIT
License-File: LICENSE
Keywords: annofab,cli,llm
Classifier: Environment :: Console
Classifier: Operating System :: OS Independent
Classifier: Programming Language :: Python :: 3.12
Classifier: Programming Language :: Python :: 3.13
Requires-Python: >=3.12
Requires-Dist: annofabapi>=1.4.7
Requires-Dist: annofabcli>=1.105.2
Requires-Dist: litellm
Requires-Dist: loguru
Requires-Dist: more-itertools
Requires-Dist: pandas<3,>=2
Requires-Dist: pyyaml
Requires-Dist: requests
